vlf4ions/__init__.py
vlf4ions/analyse_change_points.py
vlf4ions/class_definition.py
vlf4ions/compute_electron_density.py
vlf4ions/correct_phase.py
vlf4ions/detect_change_points.py
vlf4ions/flag.py
vlf4ions/forecast_nowcast.py
vlf4ions/manage_statefile.py
vlf4ions/plot_map.py
vlf4ions/polarisation.py
vlf4ions/read_files.py
vlf4ions/sunrise_sunset.py
vlf4ions-1.3.6.post3.dist-info/licenses/LICENCE.txt
vlf4ions-1.3.6.post3.dist-info/METADATA
vlf4ions-1.3.6.post3.dist-info/WHEEL
vlf4ions-1.3.6.post3.dist-info/top_level.txt
vlf4ions-1.3.6.post3.dist-info/RECORD
