Metadata-Version: 2.4
Name: vlf4ions
Version: 1.3.6.post3
Summary: Python package destined for VLF antenna owners. It allows the detection of solar flare in real-time from ground-based VLF data and an estimate of the solar X-ray flux
Author: Pauline Teysseyre for the LIRA, Carine Briand for the LIRA, Morris Cohen for Georgia Institute of Technology
Maintainer-email: Pauline Teysseyre <pauline.teysseyre@obspm.fr>
License-Expression: EUPL-1.2
Keywords: alerts,real-time,solar-flares,space-weather,vlf
License-File: LICENCE.txt
Requires-Dist: pymatreader<2,>=1.0.0
Requires-Dist: numpy<3,>=1.26.4
Requires-Dist: scipy<2,>=1.15.2
Requires-Dist: matplotlib<4,>=3.8.0
Requires-Dist: pandas<3,>=2.2.3
Requires-Dist: datetime<6,>=5.5
Requires-Dist: schedule<2,>=1.2.2
Requires-Dist: basemap<3,>=1.4.0
Requires-Dist: pysolar<2,>=0.13
Requires-Dist: pytz<2026,>=2025.2
Requires-Dist: pre-commit<5,>=4.3.0
Requires-Dist: pytest<9,>=8.3.5
Requires-Dist: coverage<8,>=7.12.0
Requires-Dist: sphinx_rtd_theme<4,>=3.0.2
Requires-Dist: defusedxml<1,>=0.7.1
Requires-Dist: genbadge<2,>=1.1.3
Dynamic: license-file
